game_master/__init__.py
game_master/__main__.py
game_master/game_master.py
game_master-0.1.3.dist-info/licenses/LICENSE
game_master-0.1.3.dist-info/METADATA
game_master-0.1.3.dist-info/WHEEL
game_master-0.1.3.dist-info/entry_points.txt
game_master-0.1.3.dist-info/top_level.txt
game_master-0.1.3.dist-info/RECORD
