Metadata-Version: 2.4
Name: game_master
Version: 0.1.3
Summary: An entertaining Python package that helps make party games more fun by providing random game ideas, challenges, and tools for game masters and party hosts.
Author-email: Tony Zhao <sz3822@nyu.edu>, Rin Qi <yq2290@nyu.edu>, Chuqiao Huang <ch3807@nyu.edu>, Huixin Li <hl4909@nyu.edu>
License:                     GNU GENERAL PUBLIC LICENSE
Project-URL: Homepage, https://github.com/software-students-spring2025/3-python-package-apexcoders
Project-URL: Repository, https://github.com/software-students-spring2025/3-python-package-apexcoders.git
Project-URL: Bug Tracker, https://github.com/software-students-spring2025/3-python-package-apexcoders/issues
Keywords: python,package,build,random
Classifier: Programming Language :: Python :: 3
Classifier: Intended Audience :: Education
Classifier: License :: OSI Approved :: GNU General Public License v3 (GPLv3)
Classifier: Operating System :: OS Independent
Requires-Python: >=3.9
License-File: LICENSE
Provides-Extra: dev
Requires-Dist: pytest; extra == "dev"
Dynamic: license-file
